setup.py
iijdns/__init__.py
iijdns/dns.py
iijdns.egg-info/PKG-INFO
iijdns.egg-info/SOURCES.txt
iijdns.egg-info/dependency_links.txt
iijdns.egg-info/requires.txt
iijdns.egg-info/top_level.txt