Metadata-Version: 1.1
Name: iijdns
Version: 0.0.2
Summary: python library(API wrapper) for IIJ DNS service
Home-page: https://github.com/samuraitaiga/python-iij-dns
Author: samuraitaiga
Author-email: samuraitaiga@gmail.com
License: MIT
Keywords: iij,dns
Platform: UNKNOWN
Classifier: License :: OSI Approved :: MIT License
Classifier: Programming Language :: Python
Classifier: Topic :: Internet :: Name Service (DNS)
Classifier: Topic :: Software Development :: Libraries :: Python Modules
